{
  "type": "genparams",
  "title": "Решение по экспертизе",
  "entityType": "order",
  "visible": true,
  "readonly": true,
  "collapse": false,
  "attributes": {
    "checkAvailableLimit": {
      "pos": 1,
      "type": "boolean",
      "format": "boolean",
      "title": "Наличие доступного лимита проверено.",
      "visible": "true",
      "required": "false",
      "readonly": "false"
    },
    "checkConditionPreventIssue": {
      "pos": 2,
      "type": "boolean",
      "format": "boolean",
      "title": "Условия препятствующие выдачи проверены.",
      "visible": "true",
      "required": "false",
      "readonly": "false"
    }
  }
}
